biomodels/__init__.py
biomodels/common.py
biomodels/identifiers.py
biomodels/metadata.py
biomodels/omex.py
biomodels/tests/test_common.py
biomodels/tests/test_download.py
biomodels-0.3.2.dist-info/LICENSE
biomodels-0.3.2.dist-info/METADATA
biomodels-0.3.2.dist-info/WHEEL
biomodels-0.3.2.dist-info/top_level.txt
biomodels-0.3.2.dist-info/RECORD
