Metadata-Version: 2.1
Name: biomodels
Version: 0.3.2
Summary: Download from the BioModels API
Author-email: Mauro Silberberg <maurosilber@gmail.com>
License: MIT License
Project-URL: Homepage, https://github.com/maurosilber/biomodels
Project-URL: Bug Tracker, https://github.com/maurosilber/biomodels/issues
Keywords: biomodels,OMEX,SBML,SED-ML
Classifier: Intended Audience :: Developers
Classifier: Intended Audience :: Science/Research
Classifier: Topic :: Scientific/Engineering
Classifier: Topic :: Software Development :: Libraries
Classifier: Programming Language :: Python :: 3
Classifier: License :: OSI Approved :: BSD License
Classifier: Operating System :: OS Independent
Requires-Python: >=3.9
License-File: LICENSE
Requires-Dist: pooch
Requires-Dist: pydantic
Requires-Dist: pydantic-xml
Requires-Dist: tabulate
Provides-Extra: test
Requires-Dist: pytest ; extra == 'test'
